tests/__init__.py
tests/conftest.py
tests/test_wwu.py
wwu/__init__.py
wwu/box.py
wwu-0.0.2.dist-info/LICENSE
wwu-0.0.2.dist-info/METADATA
wwu-0.0.2.dist-info/WHEEL
wwu-0.0.2.dist-info/top_level.txt
wwu-0.0.2.dist-info/RECORD
