Metadata-Version: 2.1
Name: wwu
Version: 0.0.2
Summary: Find the optimal way up to store your boxes.
Home-page: https://github.com/Um9i/wwu
Author: Rob Horton
Author-email: vulgarmessiah@gmail.com
License: UNKNOWN
Download-URL: https://github.com/Um9i/wwu/archive/master.zip
Keywords: boxes containers inventory permutation combinatorics
Platform: UNKNOWN
Classifier: Development Status :: 3 - Alpha
Classifier: Environment :: Console
Classifier: Intended Audience :: End Users/Desktop
Classifier: License :: OSI Approved :: MIT License
Classifier: Operating System :: OS Independent
Classifier: Topic :: Software Development :: Libraries :: Python Modules
Classifier: Topic :: Utilities
Classifier: Programming Language :: Python
